flash_attention/__init__.py
flash_attention/nn/__init__.py
flash_attention/nn/layer/__init__.py
flash_attention/nn/layer/flash_attention.py
flash_attention/ops/__init__.py
flash_attention/ops/flash_attention/__init__.py
flash_attention/ops/flash_attention/attention.py
flash_attention/ops/flash_attention/constants.py
flash_attention/ops/flash_attention/flash_attention_bwd.py
flash_attention/ops/flash_attention/flash_attention_fwd.py
flash_attention/ops/flash_attention/flash_attention_impl.py
flash_attention/ops/flash_attention/tik_ops_utils.py
flash_attention/ops/flash_attention/tiling_strategy/__init__.py
flash_attention/ops/flash_attention/tiling_strategy/sparse_tiling.py
flash_attention/ops/flash_attention/tiling_strategy/strategy.py
flash_attention/ops/flash_attention/tiling_strategy/wukong_tiling.py
flash_attention-1.0.0.dist-info/METADATA
flash_attention-1.0.0.dist-info/WHEEL
flash_attention-1.0.0.dist-info/top_level.txt
flash_attention-1.0.0.dist-info/RECORD
